fuck_denis/__init__.py
fuck_denis/fuckdenis.py
fuck_denis/fuckdenis2.py
fuckoff_denis/__init__.py
fuckoff_denis/fuckdenis.py
fuckoff_denis/fuckdenis2.py
fuckoff_denis-0.0.0.dist-info/LICENSE
fuckoff_denis-0.0.0.dist-info/METADATA
fuckoff_denis-0.0.0.dist-info/WHEEL
fuckoff_denis-0.0.0.dist-info/top_level.txt
fuckoff_denis-0.0.0.dist-info/RECORD
