Metadata-Version: 2.1
Name: fuckoff-denis
Version: 0.0.0
Summary: idk
Author: DenisFricker
License: MIT
Platform: unix
Platform: linux
Platform: osx
Platform: cygwin
Platform: win32
Classifier: Programming Language :: Python :: 3
Classifier: Programming Language :: Python :: 3 :: Only
Classifier: Programming Language :: Python :: 3.9
Classifier: Programming Language :: Python :: 3.10
Requires-Python: <3.11,>=3.9
License-File: LICENSE
Requires-Dist: numpy (>=1.20)
